ezenv.py
python_ezenv-0.0.7.dist-info/LICENSE
python_ezenv-0.0.7.dist-info/METADATA
python_ezenv-0.0.7.dist-info/WHEEL
python_ezenv-0.0.7.dist-info/top_level.txt
python_ezenv-0.0.7.dist-info/RECORD
