Metadata-Version: 2.1
Name: python-ezenv
Version: 0.0.7
Summary: Package for setting environment variable easily
Author: Enkh-Amar Ganbat
Classifier: Programming Language :: Python :: 3
Classifier: License :: OSI Approved :: MIT License
Classifier: Operating System :: OS Independent
Requires-Python: >=3.6
License-File: LICENSE
